buildlog_consultant-0.0.39.dist-info/RECORD
buildlog_consultant-0.0.39.dist-info/entry_points.txt
buildlog_consultant-0.0.39.dist-info/WHEEL
buildlog_consultant-0.0.39.dist-info/LICENSE
buildlog_consultant-0.0.39.dist-info/top_level.txt
buildlog_consultant-0.0.39.dist-info/AUTHORS
buildlog_consultant-0.0.39.dist-info/METADATA
buildlog_consultant/__main__.py
buildlog_consultant/py.typed
buildlog_consultant/apt.py
buildlog_consultant/autopkgtest.py
buildlog_consultant/__init__.py
buildlog_consultant/_buildlog_consultant_rs.pypy310-pp73-x86-linux-gnu.so
buildlog_consultant/_buildlog_consultant_rs.pyi
buildlog_consultant/sbuild.py
buildlog_consultant/common.py
