Metadata-Version: 2.1
Name: buildlog-consultant
Version: 0.0.39
Summary: buildlog parser and analyser
Author-email: Jelmer Vernooĳ <jelmer@jelmer.uk>
Project-URL: Homepage, https://github.com/jelmer/buildlog-consultant
Project-URL: Repository, https://github.com/jelmer/buildlog-consultant.git
Requires-Python: >=3.9
License-File: LICENSE
License-File: AUTHORS
Requires-Dist: python-debian
Requires-Dist: PyYAML
Requires-Dist: requirements-parser
Provides-Extra: chatgpt
Requires-Dist: openai ; extra == 'chatgpt'
Provides-Extra: dev
Requires-Dist: ruff ==0.6.1 ; extra == 'dev'
